jupyckage/__init__.py
jupyckage/jupyckage.py
jupyckage-0.1.5.data/scripts/jupyckage
jupyckage-0.1.5.dist-info/LICENSE
jupyckage-0.1.5.dist-info/METADATA
jupyckage-0.1.5.dist-info/WHEEL
jupyckage-0.1.5.dist-info/top_level.txt
jupyckage-0.1.5.dist-info/RECORD
