Metadata-Version: 2.1
Name: jupyckage
Version: 0.1.5
Summary: Create a package from a jupyter notebook
Author-email: Kerstin Frailey <frailey.work@gmail.com>
Project-URL: Homepage, https://github.com/kefrailey/jupyckage
Project-URL: Bug Tracker, https://github.com/kefrailey/jupyckage/issues
Classifier: Programming Language :: Python :: 3
Classifier: License :: OSI Approved :: MIT License
Classifier: Operating System :: OS Independent
Requires-Python: >=3.7
License-File: LICENSE
